<?xml version="1.0" encoding="UTF-8" ?><!DOCTYPE dokumente SYSTEM "http://www.gesetze-im-internet.de/dtd/1.01/gii-norm.dtd">
<dokumente builddate="20200716212549" doknr="BJNR164310020"><norm builddate="20200716212549" doknr="BJNR164310020"><metadaten><jurabk>VOV19FKG</jurabk><amtabk>COV19FKG</amtabk><ausfertigung-datum manuell="ja">2020-07-10</ausfertigung-datum><fundstelle typ="amtlich"><periodikum>BGBl I</periodikum><zitstelle>2020, 1643, 1644</zitstelle></fundstelle><kurzue>COVID-19-Gesetz zur Funktionsfähigkeit der Kammern</kurzue><langue>Gesetz zur Sicherstellung der Funktionsfähigkeit der Kammern im Bereich der Bundesrechtsanwaltsordnung, der Patentanwaltsordnung, der Bundesnotarordnung, der Wirtschaftsprüferordnung und des Steuerberatungsgesetzes während der COVID-19-Pandemie</langue><standangabe checked="ja"><standtyp>Aufh</standtyp><standkommentar>G aufgeh. durch Art. 3 Abs. 2 G v. 10.7.2020 I 1643 mWv 1.1.2022</standkommentar></standangabe></metadaten><textdaten><fussnoten><Content><P><BR/> <pre xml:space="preserve">(+++ Nachgewiesener Text noch nicht dokumentarisch bearbeitet +++)<BR/> <BR/>Das G wurde als Artikel 2 des G v. 10.7.2020 I 1643 vom Bundestag beschlossen. <BR/>Es ist gem. Art. 3 Abs. 1 Satz 3 dieses G am 17.7.2020 in Kraft getreten und <BR/>tritt gem. Art. 3 Abs. 2 dieses G mit Ablauf des 31.12.2021 außer Kraft.<BR/><BR/></pre></P></Content></fussnoten></textdaten></norm>
</dokumente>